js_invoke/__init__.py
js_invoke/core.py
js_invoke/fpm.py
js_invoke/package.py
js_invoke/push.py
js_invoke/scm.py
js_invoke/python/__init__.py
js_invoke/python/tests.py
js_invoke-2.1.9.dist-info/LICENSE.rst
js_invoke-2.1.9.dist-info/METADATA
js_invoke-2.1.9.dist-info/WHEEL
js_invoke-2.1.9.dist-info/top_level.txt
js_invoke-2.1.9.dist-info/RECORD
